pyfirebasehandler/__init__.py
pyfirebasehandler/firebase_handler.py
tests/__init__.py
tests/test_firebase_handler.py
pyfirebasehandler-9.9.9.dist-info/LICENCE
pyfirebasehandler-9.9.9.dist-info/METADATA
pyfirebasehandler-9.9.9.dist-info/WHEEL
pyfirebasehandler-9.9.9.dist-info/top_level.txt
pyfirebasehandler-9.9.9.dist-info/RECORD
