Metadata-Version: 2.1
Name: pyfirebasehandler
Version: 9.9.9
Summary: A Python module for handling a Firebase database
Author: OGENRWOTH JIM FRANK
Author-email: ogenrwoth.frank@email.com
License-File: LICENCE
Requires-Dist: firebase-admin
Requires-Dist: google-cloud-firestore
